prasticus/__init__.py
prasticus/catchall/__init__.py
prasticus/configure/__init__.py
prasticus/configure/__main__.py
prasticus/configure/engine.py
prasticus/configure/util.py
prasticus/configure/autoconfig/__init__.py
prasticus/configure/autoconfig/manageroot.py
prasticus/configure/lib/__init__.py
prasticus/configure/lib/base.py
prasticus/configure/lib/extend_module_path.py
prasticus/configure/loaded/__init__.py
prasticus-2019.7.30.dist-info/LICENSE
prasticus-2019.7.30.dist-info/METADATA
prasticus-2019.7.30.dist-info/WHEEL
prasticus-2019.7.30.dist-info/top_level.txt
prasticus-2019.7.30.dist-info/RECORD
