Metadata-Version: 2.1
Name: prasticus
Version: 2019.7.30
Summary: Projet prasticus: Catchall module extensible by plugins.
Home-page: https://sourceforge.net/projects/prasticus/
Author: Eric Ringeisen
Author-email: 
License: UNKNOWN
Platform: UNKNOWN
Classifier: Programming Language :: Python :: 3
Classifier: License :: OSI Approved :: MIT License
Classifier: Operating System :: OS Independent
Classifier: Development Status :: 4 - Beta
Classifier: Natural Language :: English
Classifier: Natural Language :: French
Classifier: Topic :: Software Development :: Libraries
Classifier: Topic :: Utilities
